{
  "meta": {
    "mode": "dynamic",
    "update_interval": 5,
    "calibrate_interval": 500,
    "representation_bias": 0.5,
    "label_bias": 0.6,
    "max_ticks": 5000,
    "seed": 42,
    "reweighting_enabled": false,
    "reweighting_mode": "none",
    "manual_group_weights": null,
    "best_online_params": {
      "tau": 0.01,
      "split_criterion": "gini",
      "remove_poor_attrs": true,
      "nb_threshold": 30,
      "merit_preprune": false,
      "max_depth": null,
      "leaf_prediction": "nba",
      "grace_period": 100,
      "delta": 1e-06,
      "binary_split": true
    },
    "mitigator_enabled": true,
    "mitigator_constraint": "demographic_parity"
  },
  "overall_metrics": {
    "roc_auc": 0.8029603674373251,
    "accuracy": 0.6870466321243524,
    "precision": 0.5577264653641207,
    "recall": 0.8555858310626703,
    "log_loss": 0.6580440569415372
  },
  "by_group": {
    "A": {
      "roc_auc": 0.7790963341858482,
      "log_loss": 0.6019755024805564,
      "accuracy": 0.7475728155339806,
      "precision": 0.7763496143958869,
      "recall": 0.8753623188405797,
      "FPR": 0.5117647058823529,
      "approval_rate": 0.7553398058252427
    },
    "B": {
      "roc_auc": 0.5610662701784197,
      "log_loss": 0.7222114026024373,
      "accuracy": 0.6177777777777778,
      "precision": 0.06896551724137931,
      "recall": 0.5454545454545454,
      "FPR": 0.37850467289719625,
      "approval_rate": 0.38666666666666666
    }
  },
  "bias_metrics": {
    "SPD": 0.3686731391585761,
    "EOD": 0.3299077733860343,
    "AOD": 0.23158390318559546,
    "PrecisionDiff": 0.7073840971545076
  },
  "per_tick": [
    {
      "tick": 0,
      "approval_rate_a": 1.0,
      "approval_rate_b": null,
      "dp_gap": null,
      "tpr_a": 1.0,
      "tpr_b": null,
      "eo_gap": null
    },
    {
      "tick": 10,
      "approval_rate_a": 0.8333333333333334,
      "approval_rate_b": 0.4,
      "dp_gap": 0.43333333333333335,
      "tpr_a": 1.0,
      "tpr_b": null,
      "eo_gap": null
    },
    {
      "tick": 20,
      "approval_rate_a": 0.6363636363636364,
      "approval_rate_b": 0.4,
      "dp_gap": 0.23636363636363633,
      "tpr_a": 0.7777777777777778,
      "tpr_b": null,
      "eo_gap": null
    },
    {
      "tick": 30,
      "approval_rate_a": 0.5555555555555556,
      "approval_rate_b": 0.3076923076923077,
      "dp_gap": 0.24786324786324787,
      "tpr_a": 0.7692307692307693,
      "tpr_b": null,
      "eo_gap": null
    },
    {
      "tick": 40,
      "approval_rate_a": 0.6,
      "approval_rate_b": 0.25,
      "dp_gap": 0.35,
      "tpr_a": 0.7894736842105263,
      "tpr_b": null,
      "eo_gap": null
    },
    {
      "tick": 50,
      "approval_rate_a": 0.5714285714285714,
      "approval_rate_b": 0.17391304347826086,
      "dp_gap": 0.39751552795031053,
      "tpr_a": 0.8,
      "tpr_b": 0.0,
      "eo_gap": 0.8
    },
    {
      "tick": 60,
      "approval_rate_a": 0.6571428571428571,
      "approval_rate_b": 0.23076923076923078,
      "dp_gap": 0.42637362637362636,
      "tpr_a": 0.8518518518518519,
      "tpr_b": 0.0,
      "eo_gap": 0.8518518518518519
    },
    {
      "tick": 70,
      "approval_rate_a": 0.6341463414634146,
      "approval_rate_b": 0.23333333333333334,
      "dp_gap": 0.4008130081300813,
      "tpr_a": 0.8387096774193549,
      "tpr_b": 0.0,
      "eo_gap": 0.8387096774193549
    },
    {
      "tick": 80,
      "approval_rate_a": 0.6595744680851063,
      "approval_rate_b": 0.23529411764705882,
      "dp_gap": 0.4242803504380475,
      "tpr_a": 0.8484848484848485,
      "tpr_b": 0.0,
      "eo_gap": 0.8484848484848485
    },
    {
      "tick": 90,
      "approval_rate_a": 0.66,
      "approval_rate_b": 0.21951219512195122,
      "dp_gap": 0.44048780487804884,
      "tpr_a": 0.8571428571428571,
      "tpr_b": 0.0,
      "eo_gap": 0.8571428571428571
    },
    {
      "tick": 100,
      "approval_rate_a": 0.6363636363636364,
      "approval_rate_b": 0.1956521739130435,
      "dp_gap": 0.4407114624505929,
      "tpr_a": 0.8611111111111112,
      "tpr_b": 0.0,
      "eo_gap": 0.8611111111111112
    },
    {
      "tick": 110,
      "approval_rate_a": 0.6666666666666666,
      "approval_rate_b": 0.17647058823529413,
      "dp_gap": 0.4901960784313725,
      "tpr_a": 0.8717948717948718,
      "tpr_b": 0.0,
      "eo_gap": 0.8717948717948718
    },
    {
      "tick": 120,
      "approval_rate_a": 0.676923076923077,
      "approval_rate_b": 0.16071428571428573,
      "dp_gap": 0.5162087912087913,
      "tpr_a": 0.8809523809523809,
      "tpr_b": 0.0,
      "eo_gap": 0.8809523809523809
    },
    {
      "tick": 130,
      "approval_rate_a": 0.6956521739130435,
      "approval_rate_b": 0.1774193548387097,
      "dp_gap": 0.5182328190743337,
      "tpr_a": 0.8888888888888888,
      "tpr_b": 0.0,
      "eo_gap": 0.8888888888888888
    },
    {
      "tick": 140,
      "approval_rate_a": 0.7105263157894737,
      "approval_rate_b": 0.18461538461538463,
      "dp_gap": 0.525910931174089,
      "tpr_a": 0.8846153846153846,
      "tpr_b": 0.0,
      "eo_gap": 0.8846153846153846
    },
    {
      "tick": 150,
      "approval_rate_a": 0.7195121951219512,
      "approval_rate_b": 0.17391304347826086,
      "dp_gap": 0.5455991516436903,
      "tpr_a": 0.8771929824561403,
      "tpr_b": 0.0,
      "eo_gap": 0.8771929824561403
    },
    {
      "tick": 160,
      "approval_rate_a": 0.7241379310344828,
      "approval_rate_b": 0.16216216216216217,
      "dp_gap": 0.5619757688723206,
      "tpr_a": 0.8852459016393442,
      "tpr_b": 0.0,
      "eo_gap": 0.8852459016393442
    },
    {
      "tick": 170,
      "approval_rate_a": 0.7362637362637363,
      "approval_rate_b": 0.15,
      "dp_gap": 0.5862637362637363,
      "tpr_a": 0.8923076923076924,
      "tpr_b": 0.0,
      "eo_gap": 0.8923076923076924
    },
    {
      "tick": 180,
      "approval_rate_a": 0.7244897959183674,
      "approval_rate_b": 0.14457831325301204,
      "dp_gap": 0.5799114826653553,
      "tpr_a": 0.8714285714285714,
      "tpr_b": 0.0,
      "eo_gap": 0.8714285714285714
    },
    {
      "tick": 190,
      "approval_rate_a": 0.7281553398058253,
      "approval_rate_b": 0.13636363636363635,
      "dp_gap": 0.5917917034421889,
      "tpr_a": 0.875,
      "tpr_b": 0.0,
      "eo_gap": 0.875
    },
    {
      "tick": 200,
      "approval_rate_a": 0.7454545454545455,
      "approval_rate_b": 0.13186813186813187,
      "dp_gap": 0.6135864135864136,
      "tpr_a": 0.8846153846153846,
      "tpr_b": 0.0,
      "eo_gap": 0.8846153846153846
    },
    {
      "tick": 210,
      "approval_rate_a": 0.7413793103448276,
      "approval_rate_b": 0.1368421052631579,
      "dp_gap": 0.6045372050816697,
      "tpr_a": 0.8795180722891566,
      "tpr_b": 0.0,
      "eo_gap": 0.8795180722891566
    },
    {
      "tick": 220,
      "approval_rate_a": 0.7419354838709677,
      "approval_rate_b": 0.13402061855670103,
      "dp_gap": 0.6079148653142668,
      "tpr_a": 0.8850574712643678,
      "tpr_b": 0.0,
      "eo_gap": 0.8850574712643678
    },
    {
      "tick": 230,
      "approval_rate_a": 0.7421875,
      "approval_rate_b": 0.1262135922330097,
      "dp_gap": 0.6159739077669903,
      "tpr_a": 0.8876404494382022,
      "tpr_b": 0.0,
      "eo_gap": 0.8876404494382022
    },
    {
      "tick": 240,
      "approval_rate_a": 0.7272727272727273,
      "approval_rate_b": 0.11926605504587157,
      "dp_gap": 0.6080066722268558,
      "tpr_a": 0.8888888888888888,
      "tpr_b": 0.0,
      "eo_gap": 0.8888888888888888
    },
    {
      "tick": 250,
      "approval_rate_a": 0.7318840579710145,
      "approval_rate_b": 0.11504424778761062,
      "dp_gap": 0.616839810183404,
      "tpr_a": 0.8842105263157894,
      "tpr_b": 0.0,
      "eo_gap": 0.8842105263157894
    },
    {
      "tick": 260,
      "approval_rate_a": 0.7172413793103448,
      "approval_rate_b": 0.11206896551724138,
      "dp_gap": 0.6051724137931034,
      "tpr_a": 0.8613861386138614,
      "tpr_b": 0.0,
      "eo_gap": 0.8613861386138614
    },
    {
      "tick": 270,
      "approval_rate_a": 0.7218543046357616,
      "approval_rate_b": 0.10833333333333334,
      "dp_gap": 0.6135209713024283,
      "tpr_a": 0.8557692307692307,
      "tpr_b": 0.0,
      "eo_gap": 0.8557692307692307
    },
    {
      "tick": 280,
      "approval_rate_a": 0.7290322580645161,
      "approval_rate_b": 0.10317460317460317,
      "dp_gap": 0.625857654889913,
      "tpr_a": 0.8598130841121495,
      "tpr_b": 0.0,
      "eo_gap": 0.8598130841121495
    },
    {
      "tick": 290,
      "approval_rate_a": 0.7295597484276729,
      "approval_rate_b": 0.09848484848484848,
      "dp_gap": 0.6310748999428244,
      "tpr_a": 0.8558558558558559,
      "tpr_b": 0.0,
      "eo_gap": 0.8558558558558559
    },
    {
      "tick": 300,
      "approval_rate_a": 0.7204968944099379,
      "approval_rate_b": 0.09285714285714286,
      "dp_gap": 0.627639751552795,
      "tpr_a": 0.8482142857142857,
      "tpr_b": 0.0,
      "eo_gap": 0.8482142857142857
    },
    {
      "tick": 310,
      "approval_rate_a": 0.725609756097561,
      "approval_rate_b": 0.08843537414965986,
      "dp_gap": 0.6371743819479011,
      "tpr_a": 0.8521739130434782,
      "tpr_b": 0.0,
      "eo_gap": 0.8521739130434782
    },
    {
      "tick": 320,
      "approval_rate_a": 0.7192982456140351,
      "approval_rate_b": 0.08666666666666667,
      "dp_gap": 0.6326315789473684,
      "tpr_a": 0.8487394957983193,
      "tpr_b": 0.0,
      "eo_gap": 0.8487394957983193
    },
    {
      "tick": 330,
      "approval_rate_a": 0.7134831460674157,
      "approval_rate_b": 0.08496732026143791,
      "dp_gap": 0.6285158258059778,
      "tpr_a": 0.8467741935483871,
      "tpr_b": 0.0,
      "eo_gap": 0.8467741935483871
    },
    {
      "tick": 340,
      "approval_rate_a": 0.7081081081081081,
      "approval_rate_b": 0.08333333333333333,
      "dp_gap": 0.6247747747747747,
      "tpr_a": 0.8449612403100775,
      "tpr_b": 0.0,
      "eo_gap": 0.8449612403100775
    },
    {
      "tick": 350,
      "approval_rate_a": 0.7120418848167539,
      "approval_rate_b": 0.08125,
      "dp_gap": 0.6307918848167539,
      "tpr_a": 0.8444444444444444,
      "tpr_b": 0.0,
      "eo_gap": 0.8444444444444444
    },
    {
      "tick": 360,
      "approval_rate_a": 0.7106598984771574,
      "approval_rate_b": 0.07926829268292683,
      "dp_gap": 0.6313916057942306,
      "tpr_a": 0.8357142857142857,
      "tpr_b": 0.0,
      "eo_gap": 0.8357142857142857
    },
    {
      "tick": 370,
      "approval_rate_a": 0.7024390243902439,
      "approval_rate_b": 0.0783132530120482,
      "dp_gap": 0.6241257713781957,
      "tpr_a": 0.8402777777777778,
      "tpr_b": 0.0,
      "eo_gap": 0.8402777777777778
    },
    {
      "tick": 380,
      "approval_rate_a": 0.7081339712918661,
      "approval_rate_b": 0.0755813953488372,
      "dp_gap": 0.6325525759430288,
      "tpr_a": 0.8435374149659864,
      "tpr_b": 0.0,
      "eo_gap": 0.8435374149659864
    },
    {
      "tick": 390,
      "approval_rate_a": 0.6995305164319249,
      "approval_rate_b": 0.07865168539325842,
      "dp_gap": 0.6208788310386665,
      "tpr_a": 0.8378378378378378,
      "tpr_b": 0.0,
      "eo_gap": 0.8378378378378378
    },
    {
      "tick": 400,
      "approval_rate_a": 0.7037037037037037,
      "approval_rate_b": 0.07567567567567568,
      "dp_gap": 0.628028028028028,
      "tpr_a": 0.8410596026490066,
      "tpr_b": 0.0,
      "eo_gap": 0.8410596026490066
    },
    {
      "tick": 410,
      "approval_rate_a": 0.695067264573991,
      "approval_rate_b": 0.07446808510638298,
      "dp_gap": 0.620599179467608,
      "tpr_a": 0.8441558441558441,
      "tpr_b": 0.0,
      "eo_gap": 0.8441558441558441
    },
    {
      "tick": 420,
      "approval_rate_a": 0.6991150442477876,
      "approval_rate_b": 0.07692307692307693,
      "dp_gap": 0.6221919673247107,
      "tpr_a": 0.8471337579617835,
      "tpr_b": 0.0,
      "eo_gap": 0.8471337579617835
    },
    {
      "tick": 430,
      "approval_rate_a": 0.7012987012987013,
      "approval_rate_b": 0.08,
      "dp_gap": 0.6212987012987014,
      "tpr_a": 0.85,
      "tpr_b": 0.0,
      "eo_gap": 0.85
    },
    {
      "tick": 440,
      "approval_rate_a": 0.6932773109243697,
      "approval_rate_b": 0.08374384236453201,
      "dp_gap": 0.6095334685598377,
      "tpr_a": 0.852760736196319,
      "tpr_b": 0.0,
      "eo_gap": 0.852760736196319
    },
    {
      "tick": 450,
      "approval_rate_a": 0.6967213114754098,
      "approval_rate_b": 0.0821256038647343,
      "dp_gap": 0.6145957076106755,
      "tpr_a": 0.8571428571428571,
      "tpr_b": 0.0,
      "eo_gap": 0.8571428571428571
    },
    {
      "tick": 460,
      "approval_rate_a": 0.6935483870967742,
      "approval_rate_b": 0.08450704225352113,
      "dp_gap": 0.6090413448432531,
      "tpr_a": 0.8538011695906432,
      "tpr_b": 0.0,
      "eo_gap": 0.8538011695906432
    },
    {
      "tick": 470,
      "approval_rate_a": 0.6968503937007874,
      "approval_rate_b": 0.08294930875576037,
      "dp_gap": 0.613901084945027,
      "tpr_a": 0.8579545454545454,
      "tpr_b": 0.0,
      "eo_gap": 0.8579545454545454
    },
    {
      "tick": 480,
      "approval_rate_a": 0.7,
      "approval_rate_b": 0.08144796380090498,
      "dp_gap": 0.6185520361990949,
      "tpr_a": 0.8611111111111112,
      "tpr_b": 0.0,
      "eo_gap": 0.8611111111111112
    },
    {
      "tick": 490,
      "approval_rate_a": 0.7052238805970149,
      "approval_rate_b": 0.08071748878923767,
      "dp_gap": 0.6245063918077772,
      "tpr_a": 0.8641304347826086,
      "tpr_b": 0.0,
      "eo_gap": 0.8641304347826086
    },
    {
      "tick": 500,
      "approval_rate_a": 0.7037037037037037,
      "approval_rate_b": 0.08225108225108226,
      "dp_gap": 0.6214526214526215,
      "tpr_a": 0.8594594594594595,
      "tpr_b": 0.0,
      "eo_gap": 0.8594594594594595
    },
    {
      "tick": 510,
      "approval_rate_a": 0.7101449275362319,
      "approval_rate_b": 0.09787234042553192,
      "dp_gap": 0.6122725871107,
      "tpr_a": 0.8638743455497382,
      "tpr_b": 0.0,
      "eo_gap": 0.8638743455497382
    },
    {
      "tick": 520,
      "approval_rate_a": 0.7163120567375887,
      "approval_rate_b": 0.11297071129707113,
      "dp_gap": 0.6033413454405175,
      "tpr_a": 0.8666666666666667,
      "tpr_b": 0.0,
      "eo_gap": 0.8666666666666667
    },
    {
      "tick": 530,
      "approval_rate_a": 0.7206896551724138,
      "approval_rate_b": 0.11618257261410789,
      "dp_gap": 0.6045070825583059,
      "tpr_a": 0.8706467661691543,
      "tpr_b": 0.0,
      "eo_gap": 0.8706467661691543
    },
    {
      "tick": 540,
      "approval_rate_a": 0.7244897959183674,
      "approval_rate_b": 0.12550607287449392,
      "dp_gap": 0.5989837230438735,
      "tpr_a": 0.8725490196078431,
      "tpr_b": 0.0,
      "eo_gap": 0.8725490196078431
    },
    {
      "tick": 550,
      "approval_rate_a": 0.7214765100671141,
      "approval_rate_b": 0.1383399209486166,
      "dp_gap": 0.5831365891184975,
      "tpr_a": 0.8689320388349514,
      "tpr_b": 0.0,
      "eo_gap": 0.8689320388349514
    },
    {
      "tick": 560,
      "approval_rate_a": 0.7260726072607261,
      "approval_rate_b": 0.1434108527131783,
      "dp_gap": 0.5826617545475478,
      "tpr_a": 0.8714285714285714,
      "tpr_b": 0.0,
      "eo_gap": 0.8714285714285714
    },
    {
      "tick": 570,
      "approval_rate_a": 0.7281553398058253,
      "approval_rate_b": 0.15648854961832062,
      "dp_gap": 0.5716667901875047,
      "tpr_a": 0.8744186046511628,
      "tpr_b": 0.0,
      "eo_gap": 0.8744186046511628
    },
    {
      "tick": 580,
      "approval_rate_a": 0.732484076433121,
      "approval_rate_b": 0.16104868913857678,
      "dp_gap": 0.5714353872945441,
      "tpr_a": 0.8767123287671232,
      "tpr_b": 0.0,
      "eo_gap": 0.8767123287671232
    },
    {
      "tick": 590,
      "approval_rate_a": 0.7366771159874608,
      "approval_rate_b": 0.16544117647058823,
      "dp_gap": 0.5712359395168726,
      "tpr_a": 0.8789237668161435,
      "tpr_b": 0.0,
      "eo_gap": 0.8789237668161435
    },
    {
      "tick": 600,
      "approval_rate_a": 0.7376543209876543,
      "approval_rate_b": 0.17689530685920576,
      "dp_gap": 0.5607590141284485,
      "tpr_a": 0.8805309734513275,
      "tpr_b": 0.1,
      "eo_gap": 0.7805309734513275
    },
    {
      "tick": 610,
      "approval_rate_a": 0.7401812688821753,
      "approval_rate_b": 0.17857142857142858,
      "dp_gap": 0.5616098403107467,
      "tpr_a": 0.8826086956521739,
      "tpr_b": 0.1,
      "eo_gap": 0.782608695652174
    },
    {
      "tick": 620,
      "approval_rate_a": 0.7440476190476191,
      "approval_rate_b": 0.19298245614035087,
      "dp_gap": 0.5510651629072683,
      "tpr_a": 0.8841201716738197,
      "tpr_b": 0.18181818181818182,
      "eo_gap": 0.702301989855638
    },
    {
      "tick": 630,
      "approval_rate_a": 0.7456140350877193,
      "approval_rate_b": 0.20069204152249134,
      "dp_gap": 0.544921993565228,
      "tpr_a": 0.8865546218487395,
      "tpr_b": 0.25,
      "eo_gap": 0.6365546218487395
    },
    {
      "tick": 640,
      "approval_rate_a": 0.7478260869565218,
      "approval_rate_b": 0.20945945945945946,
      "dp_gap": 0.5383666274970623,
      "tpr_a": 0.8870292887029289,
      "tpr_b": 0.25,
      "eo_gap": 0.6370292887029289
    },
    {
      "tick": 650,
      "approval_rate_a": 0.75,
      "approval_rate_b": 0.22442244224422442,
      "dp_gap": 0.5255775577557755,
      "tpr_a": 0.8879668049792531,
      "tpr_b": 0.3076923076923077,
      "eo_gap": 0.5802744972869454
    },
    {
      "tick": 660,
      "approval_rate_a": 0.7507082152974505,
      "approval_rate_b": 0.23376623376623376,
      "dp_gap": 0.5169419815312167,
      "tpr_a": 0.889795918367347,
      "tpr_b": 0.3076923076923077,
      "eo_gap": 0.5821036106750392
    },
    {
      "tick": 670,
      "approval_rate_a": 0.75,
      "approval_rate_b": 0.24126984126984127,
      "dp_gap": 0.5087301587301587,
      "tpr_a": 0.8906882591093117,
      "tpr_b": 0.3076923076923077,
      "eo_gap": 0.582995951417004
    },
    {
      "tick": 680,
      "approval_rate_a": 0.7548209366391184,
      "approval_rate_b": 0.24528301886792453,
      "dp_gap": 0.5095379177711938,
      "tpr_a": 0.892,
      "tpr_b": 0.3076923076923077,
      "eo_gap": 0.5843076923076923
    },
    {
      "tick": 690,
      "approval_rate_a": 0.7533875338753387,
      "approval_rate_b": 0.2546583850931677,
      "dp_gap": 0.49872914878217106,
      "tpr_a": 0.88671875,
      "tpr_b": 0.3076923076923077,
      "eo_gap": 0.5790264423076923
    },
    {
      "tick": 700,
      "approval_rate_a": 0.7533512064343163,
      "approval_rate_b": 0.2682926829268293,
      "dp_gap": 0.485058523507487,
      "tpr_a": 0.8871595330739299,
      "tpr_b": 0.4,
      "eo_gap": 0.4871595330739299
    },
    {
      "tick": 710,
      "approval_rate_a": 0.7572559366754618,
      "approval_rate_b": 0.2710843373493976,
      "dp_gap": 0.4861715993260642,
      "tpr_a": 0.8897338403041825,
      "tpr_b": 0.4,
      "eo_gap": 0.48973384030418243
    },
    {
      "tick": 720,
      "approval_rate_a": 0.7571059431524548,
      "approval_rate_b": 0.27245508982035926,
      "dp_gap": 0.48465085333209557,
      "tpr_a": 0.8843283582089553,
      "tpr_b": 0.4,
      "eo_gap": 0.48432835820895526
    },
    {
      "tick": 730,
      "approval_rate_a": 0.7576530612244898,
      "approval_rate_b": 0.28023598820059,
      "dp_gap": 0.47741707302389985,
      "tpr_a": 0.8851851851851852,
      "tpr_b": 0.4,
      "eo_gap": 0.48518518518518516
    },
    {
      "tick": 740,
      "approval_rate_a": 0.7562814070351759,
      "approval_rate_b": 0.2857142857142857,
      "dp_gap": 0.4705671213208902,
      "tpr_a": 0.8832116788321168,
      "tpr_b": 0.4,
      "eo_gap": 0.4832116788321168
    },
    {
      "tick": 750,
      "approval_rate_a": 0.7524752475247525,
      "approval_rate_b": 0.29394812680115273,
      "dp_gap": 0.45852712072359975,
      "tpr_a": 0.8745519713261649,
      "tpr_b": 0.4,
      "eo_gap": 0.4745519713261649
    },
    {
      "tick": 760,
      "approval_rate_a": 0.7493857493857494,
      "approval_rate_b": 0.2994350282485876,
      "dp_gap": 0.44995072113716184,
      "tpr_a": 0.8714285714285714,
      "tpr_b": 0.375,
      "eo_gap": 0.49642857142857144
    },
    {
      "tick": 770,
      "approval_rate_a": 0.751219512195122,
      "approval_rate_b": 0.3074792243767313,
      "dp_gap": 0.44374028781839064,
      "tpr_a": 0.8723404255319149,
      "tpr_b": 0.375,
      "eo_gap": 0.49734042553191493
    },
    {
      "tick": 780,
      "approval_rate_a": 0.751207729468599,
      "approval_rate_b": 0.31607629427792916,
      "dp_gap": 0.4351314351906699,
      "tpr_a": 0.8732394366197183,
      "tpr_b": 0.375,
      "eo_gap": 0.49823943661971826
    },
    {
      "tick": 790,
      "approval_rate_a": 0.75,
      "approval_rate_b": 0.32075471698113206,
      "dp_gap": 0.42924528301886794,
      "tpr_a": 0.8719723183391004,
      "tpr_b": 0.375,
      "eo_gap": 0.4969723183391004
    },
    {
      "tick": 800,
      "approval_rate_a": 0.7511737089201878,
      "approval_rate_b": 0.328,
      "dp_gap": 0.42317370892018774,
      "tpr_a": 0.8737201365187713,
      "tpr_b": 0.4117647058823529,
      "eo_gap": 0.4619554306364184
    },
    {
      "tick": 810,
      "approval_rate_a": 0.7517401392111369,
      "approval_rate_b": 0.3368421052631579,
      "dp_gap": 0.41489803394797903,
      "tpr_a": 0.8745762711864407,
      "tpr_b": 0.4444444444444444,
      "eo_gap": 0.43013182674199624
    },
    {
      "tick": 820,
      "approval_rate_a": 0.7528604118993135,
      "approval_rate_b": 0.3411458333333333,
      "dp_gap": 0.4117145785659802,
      "tpr_a": 0.8758389261744967,
      "tpr_b": 0.4444444444444444,
      "eo_gap": 0.43139448173005224
    },
    {
      "tick": 830,
      "approval_rate_a": 0.7562076749435666,
      "approval_rate_b": 0.3479381443298969,
      "dp_gap": 0.40826953061366966,
      "tpr_a": 0.8778877887788779,
      "tpr_b": 0.47368421052631576,
      "eo_gap": 0.4042035782525621
    },
    {
      "tick": 840,
      "approval_rate_a": 0.7577777777777778,
      "approval_rate_b": 0.35294117647058826,
      "dp_gap": 0.4048366013071895,
      "tpr_a": 0.8766233766233766,
      "tpr_b": 0.47368421052631576,
      "eo_gap": 0.4029391660970609
    },
    {
      "tick": 850,
      "approval_rate_a": 0.7555066079295154,
      "approval_rate_b": 0.3526448362720403,
      "dp_gap": 0.4028617716574751,
      "tpr_a": 0.8745980707395499,
      "tpr_b": 0.47368421052631576,
      "eo_gap": 0.4009138602132341
    },
    {
      "tick": 860,
      "approval_rate_a": 0.7559912854030502,
      "approval_rate_b": 0.35572139303482586,
      "dp_gap": 0.4002698923682243,
      "tpr_a": 0.8757961783439491,
      "tpr_b": 0.47368421052631576,
      "eo_gap": 0.4021119678176333
    },
    {
      "tick": 870,
      "approval_rate_a": 0.7548387096774194,
      "approval_rate_b": 0.35960591133004927,
      "dp_gap": 0.39523279834737013,
      "tpr_a": 0.8765822784810127,
      "tpr_b": 0.5,
      "eo_gap": 0.37658227848101267
    },
    {
      "tick": 880,
      "approval_rate_a": 0.7558386411889597,
      "approval_rate_b": 0.36097560975609755,
      "dp_gap": 0.39486303143286217,
      "tpr_a": 0.878125,
      "tpr_b": 0.5,
      "eo_gap": 0.37812500000000004
    },
    {
      "tick": 890,
      "approval_rate_a": 0.7584033613445378,
      "approval_rate_b": 0.36626506024096384,
      "dp_gap": 0.39213830110357395,
      "tpr_a": 0.8788819875776398,
      "tpr_b": 0.5,
      "eo_gap": 0.3788819875776398
    },
    {
      "tick": 900,
      "approval_rate_a": 0.7541666666666667,
      "approval_rate_b": 0.37054631828978624,
      "dp_gap": 0.3836203483768804,
      "tpr_a": 0.8792569659442725,
      "tpr_b": 0.5,
      "eo_gap": 0.3792569659442725
    },
    {
      "tick": 910,
      "approval_rate_a": 0.7546391752577319,
      "approval_rate_b": 0.3779342723004695,
      "dp_gap": 0.37670490295726244,
      "tpr_a": 0.8780487804878049,
      "tpr_b": 0.5238095238095238,
      "eo_gap": 0.35423925667828104
    },
    {
      "tick": 920,
      "approval_rate_a": 0.7551020408163265,
      "approval_rate_b": 0.3805104408352668,
      "dp_gap": 0.3745915999810597,
      "tpr_a": 0.8787878787878788,
      "tpr_b": 0.5238095238095238,
      "eo_gap": 0.35497835497835495
    },
    {
      "tick": 930,
      "approval_rate_a": 0.7555555555555555,
      "approval_rate_b": 0.3830275229357798,
      "dp_gap": 0.37252803261977574,
      "tpr_a": 0.8765060240963856,
      "tpr_b": 0.5238095238095238,
      "eo_gap": 0.3526965002868617
    },
    {
      "tick": 940,
      "approval_rate_a": 0.7534791252485089,
      "approval_rate_b": 0.3812785388127854,
      "dp_gap": 0.3722005864357235,
      "tpr_a": 0.8720238095238095,
      "tpr_b": 0.5238095238095238,
      "eo_gap": 0.3482142857142857
    },
    {
      "tick": 950,
      "approval_rate_a": 0.7549407114624506,
      "approval_rate_b": 0.3865168539325843,
      "dp_gap": 0.3684238575298663,
      "tpr_a": 0.8731563421828908,
      "tpr_b": 0.5454545454545454,
      "eo_gap": 0.32770179672834543
    },
    {
      "tick": 960,
      "approval_rate_a": 0.755859375,
      "approval_rate_b": 0.38530066815144765,
      "dp_gap": 0.37055870684855235,
      "tpr_a": 0.875,
      "tpr_b": 0.5454545454545454,
      "eo_gap": 0.3295454545454546
    }
  ]
}