{
  "meta": {
    "mode": "dynamic",
    "update_interval": 5,
    "calibrate_interval": 500,
    "representation_bias": 0.6,
    "label_bias": 0.4,
    "max_ticks": 5000,
    "seed": 42,
    "reweighting_enabled": false,
    "reweighting_mode": "none",
    "manual_group_weights": null,
    "best_online_params": {
      "tau": 0.05,
      "split_criterion": "hellinger",
      "remove_poor_attrs": true,
      "nb_threshold": 30,
      "merit_preprune": true,
      "max_depth": 5,
      "leaf_prediction": "nba",
      "grace_period": 20,
      "delta": 1e-06,
      "binary_split": false
    },
    "mitigator_enabled": false,
    "mitigator_constraint": null
  },
  "overall_metrics": {
    "roc_auc": 0.891564748530731,
    "accuracy": 0.8571428571428571,
    "precision": 0.7906976744186046,
    "recall": 0.8808290155440415,
    "log_loss": 0.8127335101710198
  },
  "by_group": {
    "A": {
      "roc_auc": 0.8350279106858054,
      "log_loss": 0.907386900520634,
      "accuracy": 0.8073089700996677,
      "precision": 0.8177339901477833,
      "recall": 0.8877005347593583,
      "FPR": 0.32456140350877194,
      "approval_rate": 0.6744186046511628
    },
    "B": {
      "roc_auc": 0.8134861932938857,
      "log_loss": 0.6499296787696833,
      "accuracy": 0.9428571428571428,
      "precision": 0.3333333333333333,
      "recall": 0.6666666666666666,
      "FPR": 0.047337278106508875,
      "approval_rate": 0.06857142857142857
    }
  },
  "bias_metrics": {
    "SPD": 0.6058471760797342,
    "EOD": 0.22103386809269165,
    "AOD": 0.24912899674747735,
    "PrecisionDiff": 0.48440065681444994
  },
  "per_tick": [
    {
      "tick": 0,
      "approval_rate_a": 1.0,
      "approval_rate_b": null,
      "dp_gap": null,
      "tpr_a": 1.0,
      "tpr_b": null,
      "eo_gap": null
    },
    {
      "tick": 10,
      "approval_rate_a": 0.875,
      "approval_rate_b": 0.6666666666666666,
      "dp_gap": 0.20833333333333337,
      "tpr_a": 1.0,
      "tpr_b": null,
      "eo_gap": null
    },
    {
      "tick": 20,
      "approval_rate_a": 0.5384615384615384,
      "approval_rate_b": 0.25,
      "dp_gap": 0.28846153846153844,
      "tpr_a": 0.8333333333333334,
      "tpr_b": null,
      "eo_gap": null
    },
    {
      "tick": 30,
      "approval_rate_a": 0.45454545454545453,
      "approval_rate_b": 0.2222222222222222,
      "dp_gap": 0.23232323232323232,
      "tpr_a": 0.7272727272727273,
      "tpr_b": null,
      "eo_gap": null
    },
    {
      "tick": 40,
      "approval_rate_a": 0.48148148148148145,
      "approval_rate_b": 0.21428571428571427,
      "dp_gap": 0.2671957671957672,
      "tpr_a": 0.6875,
      "tpr_b": null,
      "eo_gap": null
    },
    {
      "tick": 50,
      "approval_rate_a": 0.4666666666666667,
      "approval_rate_b": 0.14285714285714285,
      "dp_gap": 0.3238095238095238,
      "tpr_a": 0.7058823529411765,
      "tpr_b": null,
      "eo_gap": null
    },
    {
      "tick": 60,
      "approval_rate_a": 0.5263157894736842,
      "approval_rate_b": 0.13043478260869565,
      "dp_gap": 0.3958810068649885,
      "tpr_a": 0.75,
      "tpr_b": 0.0,
      "eo_gap": 0.75
    },
    {
      "tick": 70,
      "approval_rate_a": 0.5454545454545454,
      "approval_rate_b": 0.1111111111111111,
      "dp_gap": 0.4343434343434343,
      "tpr_a": 0.7777777777777778,
      "tpr_b": 0.0,
      "eo_gap": 0.7777777777777778
    },
    {
      "tick": 80,
      "approval_rate_a": 0.5510204081632653,
      "approval_rate_b": 0.125,
      "dp_gap": 0.42602040816326525,
      "tpr_a": 0.7931034482758621,
      "tpr_b": 0.0,
      "eo_gap": 0.7931034482758621
    },
    {
      "tick": 90,
      "approval_rate_a": 0.5636363636363636,
      "approval_rate_b": 0.1111111111111111,
      "dp_gap": 0.4525252525252525,
      "tpr_a": 0.8181818181818182,
      "tpr_b": 0.0,
      "eo_gap": 0.8181818181818182
    },
    {
      "tick": 100,
      "approval_rate_a": 0.5862068965517241,
      "approval_rate_b": 0.11627906976744186,
      "dp_gap": 0.46992782678428224,
      "tpr_a": 0.8285714285714286,
      "tpr_b": 0.5,
      "eo_gap": 0.3285714285714286
    },
    {
      "tick": 110,
      "approval_rate_a": 0.5873015873015873,
      "approval_rate_b": 0.10416666666666667,
      "dp_gap": 0.48313492063492064,
      "tpr_a": 0.8205128205128205,
      "tpr_b": 0.5,
      "eo_gap": 0.3205128205128205
    },
    {
      "tick": 120,
      "approval_rate_a": 0.6060606060606061,
      "approval_rate_b": 0.09090909090909091,
      "dp_gap": 0.5151515151515151,
      "tpr_a": 0.8333333333333334,
      "tpr_b": 0.3333333333333333,
      "eo_gap": 0.5
    },
    {
      "tick": 130,
      "approval_rate_a": 0.6,
      "approval_rate_b": 0.08196721311475409,
      "dp_gap": 0.5180327868852459,
      "tpr_a": 0.8409090909090909,
      "tpr_b": 0.3333333333333333,
      "eo_gap": 0.5075757575757576
    },
    {
      "tick": 140,
      "approval_rate_a": 0.6153846153846154,
      "approval_rate_b": 0.07936507936507936,
      "dp_gap": 0.5360195360195361,
      "tpr_a": 0.8571428571428571,
      "tpr_b": 0.3333333333333333,
      "eo_gap": 0.5238095238095237
    },
    {
      "tick": 150,
      "approval_rate_a": 0.6046511627906976,
      "approval_rate_b": 0.09230769230769231,
      "dp_gap": 0.5123434704830053,
      "tpr_a": 0.8363636363636363,
      "tpr_b": 0.5,
      "eo_gap": 0.3363636363636363
    },
    {
      "tick": 160,
      "approval_rate_a": 0.6105263157894737,
      "approval_rate_b": 0.10606060606060606,
      "dp_gap": 0.5044657097288676,
      "tpr_a": 0.8166666666666667,
      "tpr_b": 0.5,
      "eo_gap": 0.31666666666666665
    },
    {
      "tick": 170,
      "approval_rate_a": 0.61,
      "approval_rate_b": 0.09859154929577464,
      "dp_gap": 0.5114084507042254,
      "tpr_a": 0.8225806451612904,
      "tpr_b": 0.5,
      "eo_gap": 0.32258064516129037
    },
    {
      "tick": 180,
      "approval_rate_a": 0.6132075471698113,
      "approval_rate_b": 0.12,
      "dp_gap": 0.4932075471698113,
      "tpr_a": 0.8153846153846154,
      "tpr_b": 0.5,
      "eo_gap": 0.3153846153846154
    },
    {
      "tick": 190,
      "approval_rate_a": 0.6283185840707964,
      "approval_rate_b": 0.14102564102564102,
      "dp_gap": 0.4872929430451554,
      "tpr_a": 0.8260869565217391,
      "tpr_b": 0.5,
      "eo_gap": 0.32608695652173914
    },
    {
      "tick": 200,
      "approval_rate_a": 0.6260869565217392,
      "approval_rate_b": 0.12790697674418605,
      "dp_gap": 0.49817997977755313,
      "tpr_a": 0.8285714285714286,
      "tpr_b": 0.5,
      "eo_gap": 0.3285714285714286
    },
    {
      "tick": 210,
      "approval_rate_a": 0.6198347107438017,
      "approval_rate_b": 0.13333333333333333,
      "dp_gap": 0.4865013774104684,
      "tpr_a": 0.8333333333333334,
      "tpr_b": 0.6,
      "eo_gap": 0.2333333333333334
    },
    {
      "tick": 220,
      "approval_rate_a": 0.6171875,
      "approval_rate_b": 0.13978494623655913,
      "dp_gap": 0.4774025537634409,
      "tpr_a": 0.8181818181818182,
      "tpr_b": 0.6,
      "eo_gap": 0.21818181818181825
    },
    {
      "tick": 230,
      "approval_rate_a": 0.6102941176470589,
      "approval_rate_b": 0.1368421052631579,
      "dp_gap": 0.473452012383901,
      "tpr_a": 0.7951807228915663,
      "tpr_b": 0.6,
      "eo_gap": 0.1951807228915663
    },
    {
      "tick": 240,
      "approval_rate_a": 0.6197183098591549,
      "approval_rate_b": 0.1414141414141414,
      "dp_gap": 0.47830416844501344,
      "tpr_a": 0.8023255813953488,
      "tpr_b": 0.6,
      "eo_gap": 0.20232558139534884
    },
    {
      "tick": 250,
      "approval_rate_a": 0.6216216216216216,
      "approval_rate_b": 0.13592233009708737,
      "dp_gap": 0.4856992915245342,
      "tpr_a": 0.8089887640449438,
      "tpr_b": 0.6,
      "eo_gap": 0.20898876404494382
    },
    {
      "tick": 260,
      "approval_rate_a": 0.6168831168831169,
      "approval_rate_b": 0.1308411214953271,
      "dp_gap": 0.4860419953877898,
      "tpr_a": 0.8064516129032258,
      "tpr_b": 0.6,
      "eo_gap": 0.20645161290322578
    },
    {
      "tick": 270,
      "approval_rate_a": 0.6149068322981367,
      "approval_rate_b": 0.12727272727272726,
      "dp_gap": 0.48763410502540944,
      "tpr_a": 0.7959183673469388,
      "tpr_b": 0.6,
      "eo_gap": 0.1959183673469388
    },
    {
      "tick": 280,
      "approval_rate_a": 0.6121212121212121,
      "approval_rate_b": 0.1206896551724138,
      "dp_gap": 0.49143155694879825,
      "tpr_a": 0.8,
      "tpr_b": 0.6,
      "eo_gap": 0.20000000000000007
    },
    {
      "tick": 290,
      "approval_rate_a": 0.621301775147929,
      "approval_rate_b": 0.11475409836065574,
      "dp_gap": 0.5065476767872732,
      "tpr_a": 0.8058252427184466,
      "tpr_b": 0.6,
      "eo_gap": 0.2058252427184466
    },
    {
      "tick": 300,
      "approval_rate_a": 0.6206896551724138,
      "approval_rate_b": 0.11023622047244094,
      "dp_gap": 0.5104534346999728,
      "tpr_a": 0.8113207547169812,
      "tpr_b": 0.6,
      "eo_gap": 0.2113207547169812
    },
    {
      "tick": 310,
      "approval_rate_a": 0.6263736263736264,
      "approval_rate_b": 0.10852713178294573,
      "dp_gap": 0.5178464945906807,
      "tpr_a": 0.8125,
      "tpr_b": 0.6,
      "eo_gap": 0.21250000000000002
    },
    {
      "tick": 320,
      "approval_rate_a": 0.6256684491978609,
      "approval_rate_b": 0.1044776119402985,
      "dp_gap": 0.5211908372575624,
      "tpr_a": 0.8157894736842105,
      "tpr_b": 0.6,
      "eo_gap": 0.21578947368421053
    },
    {
      "tick": 330,
      "approval_rate_a": 0.6294416243654822,
      "approval_rate_b": 0.1044776119402985,
      "dp_gap": 0.5249640124251838,
      "tpr_a": 0.8181818181818182,
      "tpr_b": 0.6,
      "eo_gap": 0.21818181818181825
    },
    {
      "tick": 340,
      "approval_rate_a": 0.6305418719211823,
      "approval_rate_b": 0.10144927536231885,
      "dp_gap": 0.5290925965588634,
      "tpr_a": 0.8174603174603174,
      "tpr_b": 0.6,
      "eo_gap": 0.21746031746031746
    },
    {
      "tick": 350,
      "approval_rate_a": 0.6310679611650486,
      "approval_rate_b": 0.11724137931034483,
      "dp_gap": 0.5138265818547038,
      "tpr_a": 0.8203125,
      "tpr_b": 0.6666666666666666,
      "eo_gap": 0.15364583333333337
    },
    {
      "tick": 360,
      "approval_rate_a": 0.6303317535545023,
      "approval_rate_b": 0.11333333333333333,
      "dp_gap": 0.516998420221169,
      "tpr_a": 0.8244274809160306,
      "tpr_b": 0.5714285714285714,
      "eo_gap": 0.2529989094874592
    },
    {
      "tick": 370,
      "approval_rate_a": 0.6301369863013698,
      "approval_rate_b": 0.1118421052631579,
      "dp_gap": 0.518294881038212,
      "tpr_a": 0.8222222222222222,
      "tpr_b": 0.5714285714285714,
      "eo_gap": 0.2507936507936508
    },
    {
      "tick": 380,
      "approval_rate_a": 0.6311111111111111,
      "approval_rate_b": 0.10897435897435898,
      "dp_gap": 0.5221367521367521,
      "tpr_a": 0.8273381294964028,
      "tpr_b": 0.5714285714285714,
      "eo_gap": 0.25590955806783144
    },
    {
      "tick": 390,
      "approval_rate_a": 0.6277056277056277,
      "approval_rate_b": 0.10625,
      "dp_gap": 0.5214556277056277,
      "tpr_a": 0.823943661971831,
      "tpr_b": 0.5714285714285714,
      "eo_gap": 0.2525150905432596
    },
    {
      "tick": 400,
      "approval_rate_a": 0.6302521008403361,
      "approval_rate_b": 0.10429447852760736,
      "dp_gap": 0.5259576223127288,
      "tpr_a": 0.821917808219178,
      "tpr_b": 0.5714285714285714,
      "eo_gap": 0.25048923679060664
    },
    {
      "tick": 410,
      "approval_rate_a": 0.6296296296296297,
      "approval_rate_b": 0.10119047619047619,
      "dp_gap": 0.5284391534391535,
      "tpr_a": 0.82,
      "tpr_b": 0.5714285714285714,
      "eo_gap": 0.24857142857142855
    },
    {
      "tick": 420,
      "approval_rate_a": 0.628,
      "approval_rate_b": 0.09941520467836257,
      "dp_gap": 0.5285847953216374,
      "tpr_a": 0.8235294117647058,
      "tpr_b": 0.5714285714285714,
      "eo_gap": 0.25210084033613445
    },
    {
      "tick": 430,
      "approval_rate_a": 0.6381322957198443,
      "approval_rate_b": 0.09770114942528736,
      "dp_gap": 0.5404311462945569,
      "tpr_a": 0.8291139240506329,
      "tpr_b": 0.5714285714285714,
      "eo_gap": 0.2576853526220615
    },
    {
      "tick": 440,
      "approval_rate_a": 0.6287878787878788,
      "approval_rate_b": 0.096045197740113,
      "dp_gap": 0.5327426810477658,
      "tpr_a": 0.8209876543209876,
      "tpr_b": 0.5714285714285714,
      "eo_gap": 0.24955908289241624
    },
    {
      "tick": 450,
      "approval_rate_a": 0.6259259259259259,
      "approval_rate_b": 0.09392265193370165,
      "dp_gap": 0.5320032739922242,
      "tpr_a": 0.8192771084337349,
      "tpr_b": 0.5714285714285714,
      "eo_gap": 0.24784853700516352
    },
    {
      "tick": 460,
      "approval_rate_a": 0.6268115942028986,
      "approval_rate_b": 0.0918918918918919,
      "dp_gap": 0.5349197023110066,
      "tpr_a": 0.8176470588235294,
      "tpr_b": 0.5714285714285714,
      "eo_gap": 0.246218487394958
    },
    {
      "tick": 470,
      "approval_rate_a": 0.6312056737588653,
      "approval_rate_b": 0.08994708994708994,
      "dp_gap": 0.5412585838117754,
      "tpr_a": 0.8208092485549133,
      "tpr_b": 0.5714285714285714,
      "eo_gap": 0.24938067712634193
    },
    {
      "tick": 480,
      "approval_rate_a": 0.6401384083044983,
      "approval_rate_b": 0.08854166666666667,
      "dp_gap": 0.5515967416378317,
      "tpr_a": 0.8268156424581006,
      "tpr_b": 0.5714285714285714,
      "eo_gap": 0.2553870710295292
    },
    {
      "tick": 490,
      "approval_rate_a": 0.6498316498316499,
      "approval_rate_b": 0.08762886597938144,
      "dp_gap": 0.5622027838522684,
      "tpr_a": 0.8324324324324325,
      "tpr_b": 0.5714285714285714,
      "eo_gap": 0.2610038610038611
    },
    {
      "tick": 500,
      "approval_rate_a": 0.6546052631578947,
      "approval_rate_b": 0.09137055837563451,
      "dp_gap": 0.5632347047822601,
      "tpr_a": 0.8359788359788359,
      "tpr_b": 0.625,
      "eo_gap": 0.21097883597883593
    },
    {
      "tick": 510,
      "approval_rate_a": 0.6591639871382636,
      "approval_rate_b": 0.09,
      "dp_gap": 0.5691639871382637,
      "tpr_a": 0.8402061855670103,
      "tpr_b": 0.625,
      "eo_gap": 0.21520618556701032
    },
    {
      "tick": 520,
      "approval_rate_a": 0.6572327044025157,
      "approval_rate_b": 0.08866995073891626,
      "dp_gap": 0.5685627536635994,
      "tpr_a": 0.8434343434343434,
      "tpr_b": 0.625,
      "eo_gap": 0.21843434343434343
    },
    {
      "tick": 530,
      "approval_rate_a": 0.65527950310559,
      "approval_rate_b": 0.0861244019138756,
      "dp_gap": 0.5691551011917144,
      "tpr_a": 0.845,
      "tpr_b": 0.625,
      "eo_gap": 0.21999999999999997
    },
    {
      "tick": 540,
      "approval_rate_a": 0.6533742331288344,
      "approval_rate_b": 0.08372093023255814,
      "dp_gap": 0.5696533028962762,
      "tpr_a": 0.845771144278607,
      "tpr_b": 0.625,
      "eo_gap": 0.220771144278607
    },
    {
      "tick": 550,
      "approval_rate_a": 0.6566265060240963,
      "approval_rate_b": 0.0821917808219178,
      "dp_gap": 0.5744347252021785,
      "tpr_a": 0.8480392156862745,
      "tpr_b": 0.625,
      "eo_gap": 0.2230392156862745
    },
    {
      "tick": 560,
      "approval_rate_a": 0.6607669616519174,
      "approval_rate_b": 0.08108108108108109,
      "dp_gap": 0.5796858805708363,
      "tpr_a": 0.8483412322274881,
      "tpr_b": 0.625,
      "eo_gap": 0.22334123222748814
    },
    {
      "tick": 570,
      "approval_rate_a": 0.6540697674418605,
      "approval_rate_b": 0.07929515418502203,
      "dp_gap": 0.5747746132568385,
      "tpr_a": 0.8450704225352113,
      "tpr_b": 0.625,
      "eo_gap": 0.22007042253521125
    },
    {
      "tick": 580,
      "approval_rate_a": 0.6543909348441926,
      "approval_rate_b": 0.07894736842105263,
      "dp_gap": 0.57544356642314,
      "tpr_a": 0.8486238532110092,
      "tpr_b": 0.625,
      "eo_gap": 0.2236238532110092
    },
    {
      "tick": 590,
      "approval_rate_a": 0.6574585635359116,
      "approval_rate_b": 0.07860262008733625,
      "dp_gap": 0.5788559434485754,
      "tpr_a": 0.8513513513513513,
      "tpr_b": 0.625,
      "eo_gap": 0.22635135135135132
    },
    {
      "tick": 600,
      "approval_rate_a": 0.654891304347826,
      "approval_rate_b": 0.07725321888412018,
      "dp_gap": 0.5776380854637059,
      "tpr_a": 0.8526785714285714,
      "tpr_b": 0.625,
      "eo_gap": 0.2276785714285714
    },
    {
      "tick": 610,
      "approval_rate_a": 0.6577540106951871,
      "approval_rate_b": 0.0759493670886076,
      "dp_gap": 0.5818046436065796,
      "tpr_a": 0.8546255506607929,
      "tpr_b": 0.625,
      "eo_gap": 0.22962555066079293
    },
    {
      "tick": 620,
      "approval_rate_a": 0.662303664921466,
      "approval_rate_b": 0.07531380753138076,
      "dp_gap": 0.5869898573900852,
      "tpr_a": 0.8589743589743589,
      "tpr_b": 0.625,
      "eo_gap": 0.23397435897435892
    },
    {
      "tick": 630,
      "approval_rate_a": 0.6640826873385013,
      "approval_rate_b": 0.07377049180327869,
      "dp_gap": 0.5903121955352226,
      "tpr_a": 0.8613445378151261,
      "tpr_b": 0.625,
      "eo_gap": 0.2363445378151261
    },
    {
      "tick": 640,
      "approval_rate_a": 0.6666666666666666,
      "approval_rate_b": 0.07258064516129033,
      "dp_gap": 0.5940860215053763,
      "tpr_a": 0.8636363636363636,
      "tpr_b": 0.625,
      "eo_gap": 0.23863636363636365
    },
    {
      "tick": 650,
      "approval_rate_a": 0.665,
      "approval_rate_b": 0.07171314741035857,
      "dp_gap": 0.5932868525896414,
      "tpr_a": 0.8658536585365854,
      "tpr_b": 0.625,
      "eo_gap": 0.24085365853658536
    },
    {
      "tick": 660,
      "approval_rate_a": 0.6691176470588235,
      "approval_rate_b": 0.07114624505928854,
      "dp_gap": 0.5979714019995349,
      "tpr_a": 0.8656126482213439,
      "tpr_b": 0.625,
      "eo_gap": 0.24061264822134387
    },
    {
      "tick": 670,
      "approval_rate_a": 0.6714975845410628,
      "approval_rate_b": 0.07392996108949416,
      "dp_gap": 0.5975676234515687,
      "tpr_a": 0.867704280155642,
      "tpr_b": 0.6666666666666666,
      "eo_gap": 0.20103761348897542
    },
    {
      "tick": 680,
      "approval_rate_a": 0.6714285714285714,
      "approval_rate_b": 0.07279693486590039,
      "dp_gap": 0.5986316365626709,
      "tpr_a": 0.8664122137404581,
      "tpr_b": 0.6666666666666666,
      "eo_gap": 0.19974554707379144
    },
    {
      "tick": 690,
      "approval_rate_a": 0.6721698113207547,
      "approval_rate_b": 0.07116104868913857,
      "dp_gap": 0.6010087626316162,
      "tpr_a": 0.8674242424242424,
      "tpr_b": 0.6666666666666666,
      "eo_gap": 0.2007575757575758
    },
    {
      "tick": 700,
      "approval_rate_a": 0.6712962962962963,
      "approval_rate_b": 0.07063197026022305,
      "dp_gap": 0.6006643260360732,
      "tpr_a": 0.8666666666666667,
      "tpr_b": 0.6666666666666666,
      "eo_gap": 0.20000000000000007
    },
    {
      "tick": 710,
      "approval_rate_a": 0.6704805491990846,
      "approval_rate_b": 0.06934306569343066,
      "dp_gap": 0.601137483505654,
      "tpr_a": 0.8681318681318682,
      "tpr_b": 0.6666666666666666,
      "eo_gap": 0.20146520146520153
    },
    {
      "tick": 720,
      "approval_rate_a": 0.6749435665914221,
      "approval_rate_b": 0.07194244604316546,
      "dp_gap": 0.6030011205482566,
      "tpr_a": 0.8695652173913043,
      "tpr_b": 0.7,
      "eo_gap": 0.16956521739130437
    },
    {
      "tick": 730,
      "approval_rate_a": 0.6769911504424779,
      "approval_rate_b": 0.07168458781362007,
      "dp_gap": 0.6053065626288578,
      "tpr_a": 0.8692579505300353,
      "tpr_b": 0.7,
      "eo_gap": 0.16925795053003534
    },
    {
      "tick": 740,
      "approval_rate_a": 0.6775599128540305,
      "approval_rate_b": 0.07092198581560284,
      "dp_gap": 0.6066379270384277,
      "tpr_a": 0.8685121107266436,
      "tpr_b": 0.7,
      "eo_gap": 0.16851211072664363
    },
    {
      "tick": 750,
      "approval_rate_a": 0.6788008565310493,
      "approval_rate_b": 0.07042253521126761,
      "dp_gap": 0.6083783213197816,
      "tpr_a": 0.8711864406779661,
      "tpr_b": 0.7,
      "eo_gap": 0.17118644067796618
    },
    {
      "tick": 760,
      "approval_rate_a": 0.679324894514768,
      "approval_rate_b": 0.06968641114982578,
      "dp_gap": 0.6096384833649422,
      "tpr_a": 0.8704318936877077,
      "tpr_b": 0.7,
      "eo_gap": 0.17043189368770773
    },
    {
      "tick": 770,
      "approval_rate_a": 0.6784232365145229,
      "approval_rate_b": 0.06920415224913495,
      "dp_gap": 0.609219084265388,
      "tpr_a": 0.8721311475409836,
      "tpr_b": 0.7,
      "eo_gap": 0.1721311475409837
    },
    {
      "tick": 780,
      "approval_rate_a": 0.6809815950920245,
      "approval_rate_b": 0.0684931506849315,
      "dp_gap": 0.612488444407093,
      "tpr_a": 0.8741935483870967,
      "tpr_b": 0.7,
      "eo_gap": 0.17419354838709677
    },
    {
      "tick": 790,
      "approval_rate_a": 0.6834677419354839,
      "approval_rate_b": 0.06779661016949153,
      "dp_gap": 0.6156711317659923,
      "tpr_a": 0.8726114649681529,
      "tpr_b": 0.7,
      "eo_gap": 0.17261146496815294
    },
    {
      "tick": 800,
      "approval_rate_a": 0.6832669322709163,
      "approval_rate_b": 0.06688963210702341,
      "dp_gap": 0.6163773001638929,
      "tpr_a": 0.8742138364779874,
      "tpr_b": 0.7,
      "eo_gap": 0.1742138364779875
    },
    {
      "tick": 810,
      "approval_rate_a": 0.6844181459566075,
      "approval_rate_b": 0.06578947368421052,
      "dp_gap": 0.618628672272397,
      "tpr_a": 0.8757763975155279,
      "tpr_b": 0.7,
      "eo_gap": 0.17577639751552798
    },
    {
      "tick": 820,
      "approval_rate_a": 0.685546875,
      "approval_rate_b": 0.06796116504854369,
      "dp_gap": 0.6175857099514563,
      "tpr_a": 0.8773006134969326,
      "tpr_b": 0.7272727272727273,
      "eo_gap": 0.15002788622420526
    },
    {
      "tick": 830,
      "approval_rate_a": 0.6853281853281853,
      "approval_rate_b": 0.0670926517571885,
      "dp_gap": 0.6182355335709968,
      "tpr_a": 0.8787878787878788,
      "tpr_b": 0.7272727272727273,
      "eo_gap": 0.1515151515151515
    },
    {
      "tick": 840,
      "approval_rate_a": 0.6850094876660342,
      "approval_rate_b": 0.06687898089171974,
      "dp_gap": 0.6181305067743145,
      "tpr_a": 0.8809523809523809,
      "tpr_b": 0.7272727272727273,
      "eo_gap": 0.15367965367965364
    },
    {
      "tick": 850,
      "approval_rate_a": 0.6842105263157895,
      "approval_rate_b": 0.06583072100313479,
      "dp_gap": 0.6183798053126547,
      "tpr_a": 0.8820058997050148,
      "tpr_b": 0.7272727272727273,
      "eo_gap": 0.15473317243228746
    },
    {
      "tick": 860,
      "approval_rate_a": 0.6821561338289963,
      "approval_rate_b": 0.06501547987616099,
      "dp_gap": 0.6171406539528353,
      "tpr_a": 0.8826979472140762,
      "tpr_b": 0.7272727272727273,
      "eo_gap": 0.15542521994134895
    },
    {
      "tick": 870,
      "approval_rate_a": 0.6856617647058824,
      "approval_rate_b": 0.06422018348623854,
      "dp_gap": 0.6214415812196439,
      "tpr_a": 0.8847262247838616,
      "tpr_b": 0.6666666666666666,
      "eo_gap": 0.21805955811719502
    },
    {
      "tick": 880,
      "approval_rate_a": 0.6823956442831216,
      "approval_rate_b": 0.06363636363636363,
      "dp_gap": 0.618759280646758,
      "tpr_a": 0.8828571428571429,
      "tpr_b": 0.6666666666666666,
      "eo_gap": 0.21619047619047627
    },
    {
      "tick": 890,
      "approval_rate_a": 0.6845878136200717,
      "approval_rate_b": 0.06306306306306306,
      "dp_gap": 0.6215247505570086,
      "tpr_a": 0.884180790960452,
      "tpr_b": 0.6666666666666666,
      "eo_gap": 0.21751412429378536
    },
    {
      "tick": 900,
      "approval_rate_a": 0.6825396825396826,
      "approval_rate_b": 0.06287425149700598,
      "dp_gap": 0.6196654310426766,
      "tpr_a": 0.8848314606741573,
      "tpr_b": 0.6666666666666666,
      "eo_gap": 0.21816479400749067
    },
    {
      "tick": 910,
      "approval_rate_a": 0.6829268292682927,
      "approval_rate_b": 0.06231454005934718,
      "dp_gap": 0.6206122892089455,
      "tpr_a": 0.8861111111111111,
      "tpr_b": 0.6666666666666666,
      "eo_gap": 0.21944444444444444
    },
    {
      "tick": 920,
      "approval_rate_a": 0.6798623063683304,
      "approval_rate_b": 0.06764705882352941,
      "dp_gap": 0.6122152475448011,
      "tpr_a": 0.8870523415977961,
      "tpr_b": 0.6666666666666666,
      "eo_gap": 0.22038567493112948
    },
    {
      "tick": 930,
      "approval_rate_a": 0.6797274275979557,
      "approval_rate_b": 0.06686046511627906,
      "dp_gap": 0.6128669624816766,
      "tpr_a": 0.8858695652173914,
      "tpr_b": 0.6666666666666666,
      "eo_gap": 0.21920289855072472
    },
    {
      "tick": 940,
      "approval_rate_a": 0.6756756756756757,
      "approval_rate_b": 0.0659025787965616,
      "dp_gap": 0.6097730968791141,
      "tpr_a": 0.8858695652173914,
      "tpr_b": 0.6666666666666666,
      "eo_gap": 0.21920289855072472
    },
    {
      "tick": 950,
      "approval_rate_a": 0.6738768718801996,
      "approval_rate_b": 0.06857142857142857,
      "dp_gap": 0.605305443308771,
      "tpr_a": 0.8873994638069705,
      "tpr_b": 0.6666666666666666,
      "eo_gap": 0.22073279714030392
    }
  ]
}